odoo/addons/stock_picking_kit_components_sale_report/README.rst
odoo/addons/stock_picking_kit_components_sale_report/__init__.py
odoo/addons/stock_picking_kit_components_sale_report/__manifest__.py
odoo/addons/stock_picking_kit_components_sale_report/static/description/icon.png
odoo/addons/stock_picking_kit_components_sale_report/views/report_delivery_document.xml
odoo/addons/stock_picking_kit_components_sale_report/views/report_picking.xml
odoo12_addon_stock_picking_kit_components_sale_report-12.0.1.0.0.dist-info/METADATA
odoo12_addon_stock_picking_kit_components_sale_report-12.0.1.0.0.dist-info/WHEEL
odoo12_addon_stock_picking_kit_components_sale_report-12.0.1.0.0.dist-info/top_level.txt
odoo12_addon_stock_picking_kit_components_sale_report-12.0.1.0.0.dist-info/RECORD
